mifeco
