Metadata-Version: 1.2
Name: mifeco
Version: 1.0.5
Summary: mifeco
Home-page: https://instagram.com/rockscripts/
Author: @rockscripts
Author-email: rockscripts@gmail.com
License: UNKNOWN
Platform: any
Requires-Python: >=2.7.*
